bosesoundtouchapi/__init__.py
bosesoundtouchapi/bstappmessages.py
bosesoundtouchapi/bstconst.py
bosesoundtouchapi/bstutils.py
bosesoundtouchapi/soundtouchclient.py
bosesoundtouchapi/soundtouchdevice.py
bosesoundtouchapi/soundtouchdiscovery.py
bosesoundtouchapi/soundtoucherror.py
bosesoundtouchapi/soundtouchitemtypes.py
bosesoundtouchapi/soundtouchkeys.py
bosesoundtouchapi/soundtouchmessage.py
bosesoundtouchapi/soundtouchmodelrequest.py
bosesoundtouchapi/soundtouchnotifycategorys.py
bosesoundtouchapi/soundtouchsources.py
bosesoundtouchapi/soundtouchwarning.py
bosesoundtouchapi/docs/__init__.html
bosesoundtouchapi/docs/bosesoundtouchapi.ico
bosesoundtouchapi/docs/codecopy.js
bosesoundtouchapi/docs/index.html
bosesoundtouchapi/docs/search.js
bosesoundtouchapi/docs/bosesoundtouchapi/bstappmessages.html
bosesoundtouchapi/docs/bosesoundtouchapi/bstconst.html
bosesoundtouchapi/docs/bosesoundtouchapi/bstutils.html
bosesoundtouchapi/docs/bosesoundtouchapi/soundtouchclient.html
bosesoundtouchapi/docs/bosesoundtouchapi/soundtouchdevice.html
bosesoundtouchapi/docs/bosesoundtouchapi/soundtouchdiscovery.html
bosesoundtouchapi/docs/bosesoundtouchapi/soundtoucherror.html
bosesoundtouchapi/docs/bosesoundtouchapi/soundtouchitemtypes.html
bosesoundtouchapi/docs/bosesoundtouchapi/soundtouchkeys.html
bosesoundtouchapi/docs/bosesoundtouchapi/soundtouchmessage.html
bosesoundtouchapi/docs/bosesoundtouchapi/soundtouchmodelrequest.html
bosesoundtouchapi/docs/bosesoundtouchapi/soundtouchnotifycategorys.html
bosesoundtouchapi/docs/bosesoundtouchapi/soundtouchsources.html
bosesoundtouchapi/docs/bosesoundtouchapi/soundtouchwarning.html
bosesoundtouchapi/firmware/__init__.py
bosesoundtouchapi/firmware/soundtouchfirmware.py
bosesoundtouchapi/firmware/soundtouchfirmwareproduct.py
bosesoundtouchapi/firmware/soundtouchfirmwarerelease.py
bosesoundtouchapi/models/__init__.py
bosesoundtouchapi/models/addstation.py
bosesoundtouchapi/models/audiodspaudiomodes.py
bosesoundtouchapi-1.0.86.dist-info/LICENSE
bosesoundtouchapi-1.0.86.dist-info/METADATA
bosesoundtouchapi-1.0.86.dist-info/WHEEL
bosesoundtouchapi-1.0.86.dist-info/top_level.txt
bosesoundtouchapi-1.0.86.dist-info/RECORD
