Metadata-Version: 2.1
Name: bosesoundtouchapi
Version: 1.0.86
Summary: BOSE SoundTouch API Python3 Library
Author: Todd Lucas
Author-email: <thlucas@yahoo.com>
Project-URL: Changelog, https://github.com/thlucas1/bosesoundtouchapi/blob/master/CHANGELOG.md
Project-URL: Documentation, https://bosesoundtouchapi.readthedocs.io/en/latest/__init__.html
Project-URL: GitHub, https://github.com/thlucas1/bosesoundtouchapi
Keywords: bose,soundtouch,api,audio,speaker
Classifier: Development Status :: 5 - Production/Stable
Classifier: Intended Audience :: Developers
Classifier: Programming Language :: Python :: 3
Classifier: Operating System :: Microsoft :: Windows
Classifier: Operating System :: MacOS :: MacOS X
Classifier: Operating System :: Unix
Classifier: Topic :: Software Development :: Libraries
Classifier: Topic :: Multimedia :: Sound/Audio
Classifier: Natural Language :: English
Classifier: License :: OSI Approved :: MIT License
Requires-Python: >3.11.0
License-File: LICENSE
Requires-Dist: platformdirs >=4.1.0
Requires-Dist: requests >=2.31.0
Requires-Dist: smartinspectpython >=3.0.38
Requires-Dist: tinytag ==1.10.0
Requires-Dist: urllib3 >=2.0
Requires-Dist: websocket-client ==1.6.4
Requires-Dist: zeroconf >=0.132.2
